[
  {
    "id": "2025975397129589067",
    "text": "Washington Township, NJ (11:28 AM)\rGrid Power Outage Event\r&gt;&gt; The Ting Network detected an Electric Utility Grid Power Outage event. The event started at 11:28 AM local time and impacted at least 18 homes.\nUtility involved: ATLANTIC CITY ELECTRIC CO",
    "createdAt": "Mon Feb 23 16:45:50 +0000 2026",
    "replyCount": 0,
    "retweetCount": 0,
    "likeCount": 0,
    "conversationId": "2025975397129589067",
    "author": {
      "username": "grid_events",
      "name": "whiskerlabs-grid-event"
    },
    "authorId": "1397269331319398405"
  },
  {
    "id": "2025975392897581239",
    "text": "Del Monte Forest, CA (8:27 AM)\rGrid Power Outage Event\r&gt;&gt; The Ting Network detected an Electric Utility Grid Power Outage event. The event started at 8:27 AM local time and impacted at least 56 homes.",
    "createdAt": "Mon Feb 23 16:45:49 +0000 2026",
    "replyCount": 0,
    "retweetCount": 0,
    "likeCount": 0,
    "conversationId": "2025975392897581239",
    "author": {
      "username": "grid_events",
      "name": "whiskerlabs-grid-event"
    },
    "authorId": "1397269331319398405"
  },
  {
    "id": "2025975369417801961",
    "text": "Heathsville, VA (11:26 AM)\rGrid Power Outage Event\r&gt;&gt; The Ting Network detected an Electric Utility Grid Power Outage event. The event started at 11:26 AM local time and impacted at least 25 homes.",
    "createdAt": "Mon Feb 23 16:45:43 +0000 2026",
    "replyCount": 0,
    "retweetCount": 0,
    "likeCount": 0,
    "conversationId": "2025975369417801961",
    "author": {
      "username": "grid_events",
      "name": "whiskerlabs-grid-event"
    },
    "authorId": "1397269331319398405"
  },
  {
    "id": "2025975356344115272",
    "text": "Hillsborough Township, NJ (11:26 AM)\rGrid Power Outage Event\r&gt;&gt; The Ting Network detected an Electric Utility Grid Power Outage event. The event started at 11:26 AM local time and impacted at least 48 homes.\nUtility involved: PUBLIC SERVICE ELEC &amp; GAS CO",
    "createdAt": "Mon Feb 23 16:45:40 +0000 2026",
    "replyCount": 0,
    "retweetCount": 0,
    "likeCount": 0,
    "conversationId": "2025975356344115272",
    "author": {
      "username": "grid_events",
      "name": "whiskerlabs-grid-event"
    },
    "authorId": "1397269331319398405"
  },
  {
    "id": "2025975341655679136",
    "text": "Marion, MA (11:25 AM)\rGrid Brownout Event\r&gt;&gt; The Ting Network detected an Electric Utility Grid Brownout event. The event started at 11:25 AM local time and impacted at least 11 homes.\nUtility involved: NSTAR ELECTRIC COMPANY",
    "createdAt": "Mon Feb 23 16:45:36 +0000 2026",
    "replyCount": 0,
    "retweetCount": 0,
    "likeCount": 0,
    "conversationId": "2025975341655679136",
    "author": {
      "username": "grid_events",
      "name": "whiskerlabs-grid-event"
    },
    "authorId": "1397269331319398405"
  },
  {
    "id": "2025975336819642773",
    "text": "Nantucket, MA (11:25 AM)\rGrid Brownout Event\r&gt;&gt; The Ting Network detected an Electric Utility Grid Brownout event. The event started at 11:25 AM local time and impacted at least 14 homes.",
    "createdAt": "Mon Feb 23 16:45:35 +0000 2026",
    "replyCount": 0,
    "retweetCount": 0,
    "likeCount": 0,
    "conversationId": "2025975336819642773",
    "author": {
      "username": "grid_events",
      "name": "whiskerlabs-grid-event"
    },
    "authorId": "1397269331319398405"
  },
  {
    "id": "2025971773573914880",
    "text": "Aspen Hill, MD (11:23 AM)\rGrid Brownout Event\r&gt;&gt; The Ting Network detected an Electric Utility Grid Brownout event. The event started at 11:23 AM local time and impacted at least 51 homes.\nUtility involved: POTOMAC ELECTRIC POWER CO",
    "createdAt": "Mon Feb 23 16:31:26 +0000 2026",
    "replyCount": 0,
    "retweetCount": 0,
    "likeCount": 0,
    "conversationId": "2025971773573914880",
    "author": {
      "username": "grid_events",
      "name": "whiskerlabs-grid-event"
    },
    "authorId": "1397269331319398405"
  },
  {
    "id": "2025971749431423167",
    "text": "Silver Spring, MD (11:23 AM)\rGrid Brownout Event\r&gt;&gt; The Ting Network detected an Electric Utility Grid Brownout event. The event started at 11:23 AM local time and impacted at least 58 homes.\nUtility involved: POTOMAC ELECTRIC POWER CO",
    "createdAt": "Mon Feb 23 16:31:20 +0000 2026",
    "replyCount": 0,
    "retweetCount": 0,
    "likeCount": 0,
    "conversationId": "2025971749431423167",
    "author": {
      "username": "grid_events",
      "name": "whiskerlabs-grid-event"
    },
    "authorId": "1397269331319398405"
  },
  {
    "id": "2025971722088759407",
    "text": "Cedar Park, TX (10:22 AM)\rGrid Power Outage Event\r&gt;&gt; The Ting Network detected an Electric Utility Grid Power Outage event. The event started at 10:22 AM local time and impacted at least 36 homes.",
    "createdAt": "Mon Feb 23 16:31:13 +0000 2026",
    "replyCount": 0,
    "retweetCount": 0,
    "likeCount": 0,
    "conversationId": "2025971722088759407",
    "author": {
      "username": "grid_events",
      "name": "whiskerlabs-grid-event"
    },
    "authorId": "1397269331319398405"
  },
  {
    "id": "2025971705395429716",
    "text": "Aspen Hill, MD (11:13 AM)\rGrid Brownout Event\r&gt;&gt; The Ting Network detected an Electric Utility Grid Brownout event. The event started at 11:13 AM local time and impacted at least 37 homes.\nUtility involved: POTOMAC ELECTRIC POWER CO",
    "createdAt": "Mon Feb 23 16:31:09 +0000 2026",
    "replyCount": 0,
    "retweetCount": 0,
    "likeCount": 0,
    "conversationId": "2025971705395429716",
    "author": {
      "username": "grid_events",
      "name": "whiskerlabs-grid-event"
    },
    "authorId": "1397269331319398405"
  },
  {
    "id": "2025971687863238878",
    "text": "Aspen Hill, MD (11:13 AM)\rGrid Brownout Event\r&gt;&gt; The Ting Network detected an Electric Utility Grid Brownout event. The event started at 11:13 AM local time and impacted at least 39 homes.\nUtility involved: POTOMAC ELECTRIC POWER CO",
    "createdAt": "Mon Feb 23 16:31:05 +0000 2026",
    "replyCount": 0,
    "retweetCount": 0,
    "likeCount": 0,
    "conversationId": "2025971687863238878",
    "author": {
      "username": "grid_events",
      "name": "whiskerlabs-grid-event"
    },
    "authorId": "1397269331319398405"
  },
  {
    "id": "2025971668959563841",
    "text": "Silver Spring, MD (11:13 AM)\rGrid Brownout Event\r&gt;&gt; The Ting Network detected an Electric Utility Grid Brownout event. The event started at 11:13 AM local time and impacted at least 65 homes.\nUtility involved: POTOMAC ELECTRIC POWER CO",
    "createdAt": "Mon Feb 23 16:31:01 +0000 2026",
    "replyCount": 0,
    "retweetCount": 0,
    "likeCount": 0,
    "conversationId": "2025971668959563841",
    "author": {
      "username": "grid_events",
      "name": "whiskerlabs-grid-event"
    },
    "authorId": "1397269331319398405"
  },
  {
    "id": "2025971638525706617",
    "text": "Aspen Hill, MD (11:13 AM)\rGrid Power Outage Event\r&gt;&gt; The Ting Network detected an Electric Utility Grid Power Outage event. The event started at 11:13 AM local time and impacted at least 23 homes.\nUtility involved: POTOMAC ELECTRIC POWER CO",
    "createdAt": "Mon Feb 23 16:30:54 +0000 2026",
    "replyCount": 0,
    "retweetCount": 0,
    "likeCount": 0,
    "conversationId": "2025971638525706617",
    "author": {
      "username": "grid_events",
      "name": "whiskerlabs-grid-event"
    },
    "authorId": "1397269331319398405"
  },
  {
    "id": "2025971625917551015",
    "text": "McLean, VA (11:11 AM)\rGrid Brownout Event\r&gt;&gt; The Ting Network detected an Electric Utility Grid Brownout event. The event started at 11:11 AM local time and impacted at least 81 homes.",
    "createdAt": "Mon Feb 23 16:30:51 +0000 2026",
    "replyCount": 0,
    "retweetCount": 0,
    "likeCount": 0,
    "conversationId": "2025971625917551015",
    "author": {
      "username": "grid_events",
      "name": "whiskerlabs-grid-event"
    },
    "authorId": "1397269331319398405"
  },
  {
    "id": "2025971591243239594",
    "text": "McLean, VA (11:11 AM)\rGrid Power Outage Event\r&gt;&gt; The Ting Network detected an Electric Utility Grid Power Outage event. The event started at 11:11 AM local time and impacted at least 55 homes.",
    "createdAt": "Mon Feb 23 16:30:42 +0000 2026",
    "replyCount": 0,
    "retweetCount": 0,
    "likeCount": 0,
    "conversationId": "2025971591243239594",
    "author": {
      "username": "grid_events",
      "name": "whiskerlabs-grid-event"
    },
    "authorId": "1397269331319398405"
  },
  {
    "id": "2025971567402893588",
    "text": "Salem, SC (11:11 AM)\rGrid Power Outage Event\r&gt;&gt; The Ting Network detected an Electric Utility Grid Power Outage event. The event started at 11:11 AM local time and impacted at least 28 homes.",
    "createdAt": "Mon Feb 23 16:30:37 +0000 2026",
    "replyCount": 0,
    "retweetCount": 0,
    "likeCount": 0,
    "conversationId": "2025971567402893588",
    "author": {
      "username": "grid_events",
      "name": "whiskerlabs-grid-event"
    },
    "authorId": "1397269331319398405"
  },
  {
    "id": "2025967813630873785",
    "text": "Estell Manor, NJ (11:05 AM)\rGrid Brownout Event\r&gt;&gt; The Ting Network detected an Electric Utility Grid Brownout event. The event started at 11:05 AM local time and impacted at least 13 homes.\nUtility involved: ATLANTIC CITY ELECTRIC CO",
    "createdAt": "Mon Feb 23 16:15:42 +0000 2026",
    "replyCount": 0,
    "retweetCount": 0,
    "likeCount": 0,
    "conversationId": "2025967813630873785",
    "author": {
      "username": "grid_events",
      "name": "whiskerlabs-grid-event"
    },
    "authorId": "1397269331319398405"
  },
  {
    "id": "2025967807351988659",
    "text": "Flowood, MS (10:03 AM)\rGrid Brownout Event\r&gt;&gt; The Ting Network detected an Electric Utility Grid Brownout event. The event started at 10:03 AM local time and impacted at least 34 homes.\nUtility involved: ENTERGY MISSISSIPPI LLC",
    "createdAt": "Mon Feb 23 16:15:40 +0000 2026",
    "replyCount": 0,
    "retweetCount": 0,
    "likeCount": 0,
    "conversationId": "2025967807351988659",
    "author": {
      "username": "grid_events",
      "name": "whiskerlabs-grid-event"
    },
    "authorId": "1397269331319398405"
  },
  {
    "id": "2025967783192793452",
    "text": "Lower Township, NJ (10:55 AM)\rGrid Brownout Event\r&gt;&gt; The Ting Network detected an Electric Utility Grid Brownout event. The event started at 10:55 AM local time and impacted at least 25 homes.\nUtility involved: ATLANTIC CITY ELECTRIC CO",
    "createdAt": "Mon Feb 23 16:15:34 +0000 2026",
    "replyCount": 0,
    "retweetCount": 0,
    "likeCount": 0,
    "conversationId": "2025967783192793452",
    "author": {
      "username": "grid_events",
      "name": "whiskerlabs-grid-event"
    },
    "authorId": "1397269331319398405"
  },
  {
    "id": "2025964172849131923",
    "text": "Vienna, VA (10:50 AM)\rGrid Brownout Event\r&gt;&gt; The Ting Network detected an Electric Utility Grid Brownout event. The event started at 10:50 AM local time and impacted at least 51 homes.",
    "createdAt": "Mon Feb 23 16:01:14 +0000 2026",
    "replyCount": 0,
    "retweetCount": 0,
    "likeCount": 0,
    "conversationId": "2025964172849131923",
    "author": {
      "username": "grid_events",
      "name": "whiskerlabs-grid-event"
    },
    "authorId": "1397269331319398405"
  }
]
