[
  {
    "id": "2009266237981773928",
    "text": "December 2025 - Monthly Progress Report\n\nhttps://t.co/Qc1eRs4Ugm\n\n$SX $SXOOF https://t.co/nt4kKvH36j",
    "createdAt": "Thu Jan 08 14:09:36 +0000 2026",
    "replyCount": 2,
    "retweetCount": 2,
    "likeCount": 13,
    "conversationId": "2009266237981773928",
    "author": {
      "username": "StGeorgesPlat",
      "name": "St-Georges Eco-Mining Corp"
    },
    "authorId": "4747886801",
    "media": [
      {
        "type": "photo",
        "url": "https://pbs.twimg.com/media/G-JY-3pXsAAlZ2W.jpg",
        "width": 810,
        "height": 413,
        "previewUrl": "https://pbs.twimg.com/media/G-JY-3pXsAAlZ2W.jpg:small"
      }
    ]
  },
  {
    "id": "2000955354956611977",
    "text": "RT @miningcomau: 🎙️ Frank Dumas, Director at @StGeorgesPlat $SXOOF introduces subsidiary Iceland Resources \n🌋 Geothermal-metal program push…",
    "createdAt": "Tue Dec 16 15:45:07 +0000 2025",
    "replyCount": 0,
    "retweetCount": 5,
    "likeCount": 0,
    "conversationId": "2000955354956611977",
    "author": {
      "username": "StGeorgesPlat",
      "name": "St-Georges Eco-Mining Corp"
    },
    "authorId": "4747886801"
  },
  {
    "id": "2000331405910503642",
    "text": "St-Georges announces results of its 2025 annual general meeting of shareholders.\n\n$SX $SXOOF\n\nhttps://t.co/dvOo9eGAbW https://t.co/07Iw8UyttN",
    "createdAt": "Sun Dec 14 22:25:46 +0000 2025",
    "replyCount": 0,
    "retweetCount": 3,
    "likeCount": 12,
    "conversationId": "2000331405910503642",
    "author": {
      "username": "StGeorgesPlat",
      "name": "St-Georges Eco-Mining Corp"
    },
    "authorId": "4747886801",
    "media": [
      {
        "type": "photo",
        "url": "https://pbs.twimg.com/media/G8KayMBWgAodvBQ.jpg",
        "width": 810,
        "height": 413,
        "previewUrl": "https://pbs.twimg.com/media/G8KayMBWgAodvBQ.jpg:small"
      }
    ]
  },
  {
    "id": "1996567710596305198",
    "text": "EVSX provides corporate update\n\nhttps://t.co/LdqGX4mr5P\n\n$SX $SXOOF https://t.co/aocXzDIWHj",
    "createdAt": "Thu Dec 04 13:10:11 +0000 2025",
    "replyCount": 3,
    "retweetCount": 5,
    "likeCount": 27,
    "conversationId": "1996567710596305198",
    "author": {
      "username": "StGeorgesPlat",
      "name": "St-Georges Eco-Mining Corp"
    },
    "authorId": "4747886801",
    "media": [
      {
        "type": "photo",
        "url": "https://pbs.twimg.com/media/G7U7taNXcAA5S_0.jpg",
        "width": 810,
        "height": 413,
        "previewUrl": "https://pbs.twimg.com/media/G7U7taNXcAA5S_0.jpg:small"
      }
    ]
  },
  {
    "id": "1995477766527922446",
    "text": "St-Georges reports improved financial results for the six months ended September 30, 2025\n\n$SX $SXOOF\n\nhttps://t.co/iCvgiX34DA https://t.co/AbIv4PpJF0",
    "createdAt": "Mon Dec 01 12:59:08 +0000 2025",
    "replyCount": 1,
    "retweetCount": 2,
    "likeCount": 21,
    "conversationId": "1995477766527922446",
    "author": {
      "username": "StGeorgesPlat",
      "name": "St-Georges Eco-Mining Corp"
    },
    "authorId": "4747886801",
    "media": [
      {
        "type": "photo",
        "url": "https://pbs.twimg.com/media/G7FcavbXMAAMhL4.jpg",
        "width": 810,
        "height": 413,
        "previewUrl": "https://pbs.twimg.com/media/G7FcavbXMAAMhL4.jpg:small"
      }
    ]
  },
  {
    "id": "1988957626525458638",
    "text": "High-Grade Nickel and Platinum Group Metal Discovery Expands Manicouagan Critical Minerals Potential\n\nhttps://t.co/knk0hfBVNK\n\n$SX $SXOOF https://t.co/ZOMqcJh8zt",
    "createdAt": "Thu Nov 13 13:10:25 +0000 2025",
    "replyCount": 1,
    "retweetCount": 8,
    "likeCount": 32,
    "conversationId": "1988957626525458638",
    "author": {
      "username": "StGeorgesPlat",
      "name": "St-Georges Eco-Mining Corp"
    },
    "authorId": "4747886801",
    "media": [
      {
        "type": "photo",
        "url": "https://pbs.twimg.com/media/G5oyZlGX0AAqwGV.jpg",
        "width": 892,
        "height": 673,
        "previewUrl": "https://pbs.twimg.com/media/G5oyZlGX0AAqwGV.jpg:small"
      }
    ]
  },
  {
    "id": "1986931393801130301",
    "text": "October 2025 - Monthly Progress Report\n\nhttps://t.co/fpGGOHN1uY\n\n$SX $SXOOF https://t.co/8GqeG0nbE7",
    "createdAt": "Fri Nov 07 22:58:54 +0000 2025",
    "replyCount": 0,
    "retweetCount": 2,
    "likeCount": 18,
    "conversationId": "1986931393801130301",
    "author": {
      "username": "StGeorgesPlat",
      "name": "St-Georges Eco-Mining Corp"
    },
    "authorId": "4747886801",
    "media": [
      {
        "type": "photo",
        "url": "https://pbs.twimg.com/media/G5L_jrOWUAAbco4.jpg",
        "width": 810,
        "height": 413,
        "previewUrl": "https://pbs.twimg.com/media/G5L_jrOWUAAbco4.jpg:small"
      }
    ]
  },
  {
    "id": "1976678478012629163",
    "text": "The answers to this edition of The 5 with SX are now live.\n\nWe've selected five insightful questions to address &amp; fixed moderation issues triggered by a targetted \"scrutinity\".\n\n🗣️ Read the answers here: \nhttps://t.co/nETkSXell8\n\nThank you for your participation. \n\n$SX $SXOOF",
    "createdAt": "Fri Oct 10 15:57:28 +0000 2025",
    "replyCount": 1,
    "retweetCount": 2,
    "likeCount": 8,
    "conversationId": "1976678478012629163",
    "author": {
      "username": "StGeorgesPlat",
      "name": "St-Georges Eco-Mining Corp"
    },
    "authorId": "4747886801"
  },
  {
    "id": "1976082548628521167",
    "text": "The 5 with SX won't be available tonight, Our apologies.\n\nThe answers scheduled for October 8 are running into moderation issues. We will try to resolve the problem over the next few days.\n\n#reddit  #redditmoderation https://t.co/U3W4gaOxBW",
    "createdAt": "Thu Oct 09 00:29:28 +0000 2025",
    "replyCount": 1,
    "retweetCount": 1,
    "likeCount": 7,
    "conversationId": "1976082548628521167",
    "author": {
      "username": "StGeorgesPlat",
      "name": "St-Georges Eco-Mining Corp"
    },
    "authorId": "4747886801",
    "media": [
      {
        "type": "photo",
        "url": "https://pbs.twimg.com/media/G2xz0r9WEAAI5a-.png",
        "width": 1342,
        "height": 457,
        "previewUrl": "https://pbs.twimg.com/media/G2xz0r9WEAAI5a-.png:small"
      }
    ]
  },
  {
    "id": "1960813883733516609",
    "text": "The answers to this edition of The 5 with SX are now live.\n\nWe've selected five insightful questions to address.\n\n🗣️ Read the answers here: https://t.co/nETkSXdNvA\n\nThank you for your participation. \n\n$SX $SXOOF",
    "createdAt": "Wed Aug 27 21:17:14 +0000 2025",
    "replyCount": 0,
    "retweetCount": 1,
    "likeCount": 11,
    "conversationId": "1960813883733516609",
    "author": {
      "username": "StGeorgesPlat",
      "name": "St-Georges Eco-Mining Corp"
    },
    "authorId": "4747886801"
  },
  {
    "id": "1948355876978343937",
    "text": "EVSX Expands Leadership Team\n\n$SX $SXOOF\n\nhttps://t.co/2bSrQD9pRa https://t.co/89h4mj4jVm",
    "createdAt": "Thu Jul 24 12:13:34 +0000 2025",
    "replyCount": 1,
    "retweetCount": 5,
    "likeCount": 39,
    "conversationId": "1948355876978343937",
    "author": {
      "username": "StGeorgesPlat",
      "name": "St-Georges Eco-Mining Corp"
    },
    "authorId": "4747886801",
    "media": [
      {
        "type": "photo",
        "url": "https://pbs.twimg.com/media/GwnzTvcXUAEZH_w.jpg",
        "width": 810,
        "height": 413,
        "previewUrl": "https://pbs.twimg.com/media/GwnzTvcXUAEZH_w.jpg:small"
      }
    ]
  },
  {
    "id": "1937991612438876468",
    "text": "The answers to this edition of The 5 with SX are now live.\n\nWe've selected five insightful questions to address.\n\n🗣️ Read the answers here: https://t.co/nETkSXell8\n\nThank you for your participation. \n\n$SX $SXOOF",
    "createdAt": "Wed Jun 25 21:49:41 +0000 2025",
    "replyCount": 0,
    "retweetCount": 1,
    "likeCount": 7,
    "conversationId": "1937991612438876468",
    "author": {
      "username": "StGeorgesPlat",
      "name": "St-Georges Eco-Mining Corp"
    },
    "authorId": "4747886801"
  },
  {
    "id": "1934570399272218975",
    "text": "The 5 with SX is here.\n\n📬 Submit questions to public@stgeorgesecomining.com with the subject \"Reddit Q&amp;A\" by June 20 at 17h ET. \n\nOnly questions via email will be answered.\n\n📅 Answers posted June 25 on our Reddit: https://t.co/nETkSXell8\n$SX $SXOOF",
    "createdAt": "Mon Jun 16 11:15:00 +0000 2025",
    "replyCount": 0,
    "retweetCount": 0,
    "likeCount": 5,
    "conversationId": "1934570399272218975",
    "author": {
      "username": "StGeorgesPlat",
      "name": "St-Georges Eco-Mining Corp"
    },
    "authorId": "4747886801"
  },
  {
    "id": "1932922037951213806",
    "text": "The answers to this edition of The 5 with SX are now live.\n\n🗣️ Read the answers here: \nhttps://t.co/nETkSXell8\n\nThank you for your participation. \n\n$SX $SXOOF",
    "createdAt": "Wed Jun 11 22:05:00 +0000 2025",
    "replyCount": 1,
    "retweetCount": 2,
    "likeCount": 7,
    "conversationId": "1932922037951213806",
    "author": {
      "username": "StGeorgesPlat",
      "name": "St-Georges Eco-Mining Corp"
    },
    "authorId": "4747886801"
  },
  {
    "id": "1930446880275661174",
    "text": "Monthly Progress Report - May 2025\n\nhttps://t.co/wI5qN10T0w\n\n$SX $SXOOF https://t.co/ZXROqSgLd4",
    "createdAt": "Thu Jun 05 02:09:36 +0000 2025",
    "replyCount": 1,
    "retweetCount": 3,
    "likeCount": 23,
    "conversationId": "1930446880275661174",
    "author": {
      "username": "StGeorgesPlat",
      "name": "St-Georges Eco-Mining Corp"
    },
    "authorId": "4747886801",
    "media": [
      {
        "type": "photo",
        "url": "https://pbs.twimg.com/media/GspTHB6XoAAoBtQ.jpg",
        "width": 810,
        "height": 413,
        "previewUrl": "https://pbs.twimg.com/media/GspTHB6XoAAoBtQ.jpg:small"
      }
    ]
  },
  {
    "id": "1922765111158034533",
    "text": "The answers to this edition of The 5 with SX are now live.\n\nWe've selected five insightful questions to address.\n\n🗣️ Read the answers here:\n https://t.co/nETkSXdNvA\n\nThank you for your participation. \n\n$SX $SXOOF",
    "createdAt": "Wed May 14 21:25:00 +0000 2025",
    "replyCount": 1,
    "retweetCount": 0,
    "likeCount": 10,
    "conversationId": "1922765111158034533",
    "author": {
      "username": "StGeorgesPlat",
      "name": "St-Georges Eco-Mining Corp"
    },
    "authorId": "4747886801"
  },
  {
    "id": "1915149975949894124",
    "text": "The answers to this edition of The 5 with SX are now live.\n\nWe've selected some insightful questions to address.\n🗣️ Read the answers here: \nhttps://t.co/nETkSXdNvA\n\nThank you for your participation. \n\n$SX $SXOOF",
    "createdAt": "Wed Apr 23 21:05:10 +0000 2025",
    "replyCount": 1,
    "retweetCount": 0,
    "likeCount": 8,
    "conversationId": "1915149975949894124",
    "author": {
      "username": "StGeorgesPlat",
      "name": "St-Georges Eco-Mining Corp"
    },
    "authorId": "4747886801"
  },
  {
    "id": "1914707603994595377",
    "text": "As we mark #EarthDay2025  we are reminded of the critical role each of us plays in shaping a more sustainable future\n\nOur commitment to environmental responsibility is at the heart of everything we do\n\nThrough our battery recycling initiatives, we will close the loop on critical minerals, reducing waste, and helping the transition toward cleaner energy \n\nEvery battery we will recover or repurpose represents a step toward a circular economy—where materials are reused, not wasted\n\nWe are proud to be part of the solution, developing safe & efficient technologies that not only reduce our environmental footprint but also create long-term value\n\nTogether, we are powering a cleaner, more sustainable tomorrow     #SX #SXOOF",
    "createdAt": "Tue Apr 22 15:47:20 +0000 2025",
    "replyCount": 0,
    "retweetCount": 5,
    "likeCount": 23,
    "conversationId": "1914707603994595377",
    "author": {
      "username": "StGeorgesPlat",
      "name": "St-Georges Eco-Mining Corp"
    },
    "authorId": "4747886801",
    "media": [
      {
        "type": "photo",
        "url": "https://pbs.twimg.com/media/GpJoPy2XMAAPxQb.jpg",
        "width": 1077,
        "height": 718,
        "previewUrl": "https://pbs.twimg.com/media/GpJoPy2XMAAPxQb.jpg:small"
      }
    ]
  },
  {
    "id": "1910077399930221000",
    "text": "The answers to this edition of The 5 with SX are now live.\n\nWe've selected three insightful questions to address.\n\n🗣️ Read the answers here: https://t.co/nETkSXdNvA\nThank you for your participation. \n\n$SX $SXOOF",
    "createdAt": "Wed Apr 09 21:08:34 +0000 2025",
    "replyCount": 0,
    "retweetCount": 2,
    "likeCount": 15,
    "conversationId": "1910077399930221000",
    "author": {
      "username": "StGeorgesPlat",
      "name": "St-Georges Eco-Mining Corp"
    },
    "authorId": "4747886801"
  },
  {
    "id": "1909281522508530131",
    "text": "The 5 with SX is here.\n\n📬 Submit questions to public@stgeorgesecomining.com with the subject \"Reddit Q&amp;A\" by April 18 at 17h ET. \nOnly questions via email will be answered.\n\n📅 Answers posted April 23 on our Reddit: https://t.co/nETkSXdNvA\n\n$SX $SXOOF",
    "createdAt": "Mon Apr 07 16:26:02 +0000 2025",
    "replyCount": 0,
    "retweetCount": 1,
    "likeCount": 9,
    "conversationId": "1909281522508530131",
    "author": {
      "username": "StGeorgesPlat",
      "name": "St-Georges Eco-Mining Corp"
    },
    "authorId": "4747886801"
  }
]
